htmap/__init__.py
htmap/__main__.py
htmap/_startup.py
htmap/checkpointing.py
htmap/cli.py
htmap/condor.py
htmap/errors.py
htmap/exceptions.py
htmap/holds.py
htmap/htio.py
htmap/management.py
htmap/mapped.py
htmap/mapping.py
htmap/maps.py
htmap/names.py
htmap/options.py
htmap/settings.py
htmap/state.py
htmap/tags.py
htmap/transfer.py
htmap/types.py
htmap/utils.py
htmap/version.py
htmap/run/__init__.py
htmap/run/_htmap_run.bat
htmap/run/_htmap_run.py
htmap/run/_htmap_run.sh
htmap/run/_htmap_run_with_singularity.sh
htmap/run/_htmap_run_with_transplant.sh
htmap/run/_htmap_transfer_plugin.py
htmap-0.6.1.dist-info/LICENSE
htmap-0.6.1.dist-info/METADATA
htmap-0.6.1.dist-info/WHEEL
htmap-0.6.1.dist-info/entry_points.txt
htmap-0.6.1.dist-info/top_level.txt
htmap-0.6.1.dist-info/RECORD
