Metadata-Version: 2.1
Name: htmap
Version: 0.6.1
Summary: High-Throughput Computing in Python, powered by HTCondor
Home-page: https://github.com/htcondor/htmap
Author: Josh Karpel
Author-email: josh.karpel@gmail.com
License: Apache-2.0
Platform: UNKNOWN
Classifier: Development Status :: 3 - Alpha
Classifier: Intended Audience :: Developers
Classifier: Intended Audience :: Science/Research
Classifier: License :: OSI Approved :: Apache Software License
Classifier: Operating System :: OS Independent
Classifier: Programming Language :: Python :: 3
Classifier: Programming Language :: Python :: 3 :: Only
Classifier: Programming Language :: Python :: 3.6
Classifier: Programming Language :: Python :: 3.7
Classifier: Programming Language :: Python :: 3.8
Classifier: Topic :: System :: Distributed Computing
Requires-Python: >=3.6
Requires-Dist: click (>=7.0)
Requires-Dist: click-didyoumean (>=0.0.3)
Requires-Dist: cloudpickle (>=1.4)
Requires-Dist: halo (>=0.0.30)
Requires-Dist: htcondor (>=8.8)
Requires-Dist: toml (>=0.10)
Requires-Dist: tqdm (>=4.46)
Requires-Dist: importlib-metadata (>=1.0) ; python_version < "3.8"
Provides-Extra: docs
Requires-Dist: ipython ; extra == 'docs'
Requires-Dist: nbsphinx ; extra == 'docs'
Requires-Dist: nbstripout ; extra == 'docs'
Requires-Dist: pygments-github-lexers ; extra == 'docs'
Requires-Dist: sphinx ; extra == 'docs'
Requires-Dist: sphinx-autobuild ; extra == 'docs'
Requires-Dist: sphinx-click ; extra == 'docs'
Requires-Dist: sphinx-issues ; extra == 'docs'
Requires-Dist: sphinx-autodoc-typehints ; extra == 'docs'
Requires-Dist: sphinx-rtd-theme ; extra == 'docs'
Provides-Extra: tests
Requires-Dist: codecov ; extra == 'tests'
Requires-Dist: coverage ; extra == 'tests'
Requires-Dist: pre-commit ; extra == 'tests'
Requires-Dist: pytest (>=6) ; extra == 'tests'
Requires-Dist: pytest-cov ; extra == 'tests'
Requires-Dist: pytest-mock ; extra == 'tests'
Requires-Dist: pytest-profiling ; extra == 'tests'
Requires-Dist: pytest-timeout ; extra == 'tests'
Requires-Dist: pytest-watch ; extra == 'tests'
Requires-Dist: pytest-xdist ; extra == 'tests'
